LICENSE
README.md
pyproject.toml
setup.cfg
src/openmovement/__init__.py
src/openmovement.egg-info/PKG-INFO
src/openmovement.egg-info/SOURCES.txt
src/openmovement.egg-info/dependency_links.txt
src/openmovement.egg-info/requires.txt
src/openmovement.egg-info/top_level.txt
src/openmovement/load/__init__.py
src/openmovement/load/base_data.py
src/openmovement/load/csv_load.py
src/openmovement/load/cwa_load.py
src/openmovement/load/multi_load.py
src/openmovement/load/wav_load.py
src/openmovement/load/zip_helper.py
src/openmovement/process/__init__.py
src/openmovement/process/calc_svm.py
src/openmovement/process/calc_wtv.py
src/openmovement/process/epoch.py
src/openmovement/process/omconvert.py