Metadata-Version: 2.1
Name: openmovement
Version: 0.0.1
Summary: Open Movement processing code
Home-page: https://github.com/digitalinteraction/openmovement-python/
Author: Daniel Jackson
License: UNKNOWN
Project-URL: Bug Tracker, https://github.com/digitalinteraction/openmovement-python/issues
Platform: UNKNOWN
Classifier: Programming Language :: Python :: 3
Classifier: License :: OSI Approved :: BSD License
Classifier: Operating System :: OS Independent
Classifier: Environment :: Console
Classifier: Intended Audience :: Science/Research
Classifier: Topic :: Scientific/Engineering :: Information Analysis
Classifier: Development Status :: 2 - Pre-Alpha
Requires-Python: >=3.6
License-File: LICENSE
